stockSentiment/__init__.py
stockSentiment/server.py
stock_sentiment-0.1.1.dist-info/licenses/LICENSE
stock_sentiment-0.1.1.dist-info/METADATA
stock_sentiment-0.1.1.dist-info/WHEEL
stock_sentiment-0.1.1.dist-info/entry_points.txt
stock_sentiment-0.1.1.dist-info/top_level.txt
stock_sentiment-0.1.1.dist-info/RECORD
