Metadata-Version: 2.4
Name: stock-sentiment
Version: 0.1.1
Summary: A simple MCP server for stock news and sentiment using Alpha Vantage.
Author-email: Mohd Arham Islam <arhamislam@gmail.com>
License: MIT
Project-URL: Homepage, https://pypi.org/project/stock-sentiment/
Requires-Python: >=3.8
License-File: LICENSE
Requires-Dist: httpx
Requires-Dist: python-dotenv
Requires-Dist: mcp
Dynamic: license-file
